githubfucker/__init__.py
githubfucker/cli.py
githubfucker-1.0.2.dist-info/METADATA
githubfucker-1.0.2.dist-info/WHEEL
githubfucker-1.0.2.dist-info/entry_points.txt
githubfucker-1.0.2.dist-info/top_level.txt
githubfucker-1.0.2.dist-info/RECORD
