Metadata-Version: 2.4
Name: githubfucker
Version: 1.0.2
Summary: Dev All-in-One Accelerator (Github, Pip, Docker, Apt, UV)
Home-page: https://github.com/pythonxueba
Author: pythonxueba
Classifier: Programming Language :: Python :: 3
Classifier: License :: OSI Approved :: MIT License
Classifier: Operating System :: OS Independent
Requires-Python: >=3.6
Requires-Dist: requests
Requires-Dist: colorama
Dynamic: author
Dynamic: classifier
Dynamic: description
Dynamic: description-content-type
Dynamic: home-page
Dynamic: requires-dist
Dynamic: requires-python
Dynamic: summary
